<story>
<id>682295</id>
<state>1</state>
<story_issue>no</story_issue>
<select_magazine>0</select_magazine>
<select_supplement/>
<issue_date/>
<bylines>
<byline>290</byline>
</bylines>
<createddate>1464764322</createddate>
<publisheddate>1464764262</publisheddate>
<modifieddate>1464774228</modifieddate>
<createdby>704</createdby>
<modifiedby>704</modifiedby>
<cities>
<city>285563</city>
</cities>
<categories><category>279986</category><category>279631</category><category>280185</category><category>279607</category></categories><ordering>682295</ordering><primarycategory>279607</primarycategory><extralargeimage><![CDATA[http://media2.intoday.in/indiatoday/images/stories/sc-8_647_032916081957_060116124839.jpg]]></extralargeimage>
<extra_large_alt><![CDATA[Picture for representational purpose]]></extra_large_alt>
<extra_large_title><![CDATA[Picture for representational purpose]]></extra_large_title>
<largeimage><![CDATA[http://media2.intoday.in/indiatoday/images/stories/sc-8_305_032916081957_060116124839.jpg]]></largeimage>
<large_alt><![CDATA[Picture for representational purpose]]></large_alt>
<large_title><![CDATA[Picture for representational purpose]]></large_title>
<mediumimage><![CDATA[http://media2.intoday.in/indiatoday/images/stories/sc-8_300x350_032916081957_060116124839.jpg]]></mediumimage>
<mediumimage_alt><![CDATA[Picture for representational purpose]]></mediumimage_alt>
<mediumimage_title><![CDATA[Picture for representational purpose]]></mediumimage_title>
<smallimage><![CDATA[http://media2.intoday.in/indiatoday/images/stories/sc-8_180_032916081957_060116124811.jpg]]></smallimage>
<smallimage_alt><![CDATA[Picture for representational purpose]]></smallimage_alt>
<smallimage_title><![CDATA[Picture for representational purpose]]></smallimage_title>
<extrasmallimage><![CDATA[http://media2.intoday.in/indiatoday/images/stories/sc-8_88_032916081957_060116124839.jpg]]></extrasmallimage>
<extra_small_alt><![CDATA[Picture for representational purpose]]></extra_small_alt>
<extra_small_title><![CDATA[Picture for representational purpose]]></extra_small_title>
<bigimage/>
<kicker_image_caption/>
<mosimage>
<image/><caption/></mosimage>
<pros_cons><tech_pros_cons_main><title/><rating/><pron_cons_img/></tech_pros_cons_main><tech_pros><item/><item/><item/></tech_pros><tech_cons><item/><item/></tech_cons></pros_cons><tech-image-gallery><image/></tech-image-gallery><fulltext_conclaveformat><listicle_title><![CDATA[]]></listicle_title><quote_title/><factoids_title/><quote_image/>
<listicle_content><listicle><![CDATA[In its letter, the women\'s rights group claims that 92 per cent Muslim women are against triple talaq and want it to be abolished.]]></listicle><listicle><![CDATA[\"We have found that women want a legal ban on the practice of oral/unilateral divorce. Our national study \'Seeking Justice Within Family\' found that 92 per cent of Muslim women want an end to this practice which destroys their life and the lives of their children. Coupled with oral divorce is the heinous practice of nikah halala which also must be abolished,\" Kumaramangalam said.]]></listicle><listicle><![CDATA[The body has also said that verbal divorce finds no mention in the Quran and such a practice is un-Islamic.]]></listicle><listicle><![CDATA[They are demanding that the Muslim personal law be amended to safeguard Muslim women\'s rights.]]></listicle><listicle><![CDATA[The body said that on a mere pronouncement of talaq thrice, the woman gets instantly and irrevocably divorced and becomes a \"destitute\" overnight.]]></listicle><listicle><![CDATA[The women\'s body also sought equal citizenship rights for Muslims as enshrined in the Constitution as well as justice and equality for Muslim women based on the \"Quranic tenets\".]]></listicle><listicle><![CDATA[Interestingly, many Muslim countries, like Pakistan and Indonesia, a country that has the largest Muslim population, have banned triple talaq.]]></listicle></listicle_content>
<quotes><quote/></quotes>
<factoids_content><factoids/>
</factoids_content>
</fulltext_conclaveformat>
<storykicker><![CDATA[The chorus against triple talaq, among Muslims in the country, is growing. Members of a women's rights group have sought the support of the NCW to abolish the practice of triple talaq.<br />]]></storykicker>
<storybody><![CDATA[<p>Members of a women's rights group have approached the National Commission for Women (NCW) seeking its support to abolish the practice of triple talaq, terming it as an "un-Quranic" practice.</p><p>The Bharatiya Muslim Mahila Andolan in its letter to NCW chief Lalitha Kumaramangalam claimed that it has collected 50,000 signatures in support of its campaign and is writing to Women's Commissions of different states for their support.</p><p><b>HERE'S WHAT YOU SHOULD KNOW:</b><br /></p>                    {funfacts}<div class="conclace-story-wrapper"><div class="dotted-line"></div><div class="conclace-heading"></div>
							<div class="facts">
								<ol><li><div>In its letter, the women's rights group claims that 92 per cent Muslim women are against triple talaq and want it to be abolished.</div></li><li><div>"We have found that women want a legal ban on the practice of oral/unilateral divorce. Our national study 'Seeking Justice Within Family' found that 92 per cent of Muslim women want an end to this practice which destroys their life and the lives of their children. Coupled with oral divorce is the heinous practice of nikah halala which also must be abolished," Kumaramangalam said.</div></li><li><div>The body has also said that verbal divorce finds no mention in the Quran and such a practice is un-Islamic.</div></li><li><div>They are demanding that the Muslim personal law be amended to safeguard Muslim women's rights.</div></li><li><div>The body said that on a mere pronouncement of talaq thrice, the woman gets instantly and irrevocably divorced and becomes a "destitute" overnight.</div></li><li><div>The women's body also sought equal citizenship rights for Muslims as enshrined in the Constitution as well as justice and equality for Muslim women based on the "Quranic tenets".</div></li><li><div>Interestingly, many Muslim countries, like Pakistan and Indonesia, a country that has the largest Muslim population, have banned triple talaq.</div></li></ol></div><div style="margin-top: -9px;" class="dotted-line"></div><div class="dotted-line"></div></div>{funfacts}                    <p><a href="http://indiatoday.intoday.in/story/nri-man-sends-talaq-shocker-to-wife-on-whatsapp/1/492903.html" target="_blank" mce_href="http://indiatoday.intoday.in/story/nri-man-sends-talaq-shocker-to-wife-on-whatsapp/1/492903.html"><b>ALSO READ | NRI man sends Talaq shocker to wife on WhatsApp</b></a> <br /></p>]]></storybody>
<magazinekicker><![CDATA[The chorus against triple talaq, among Muslims in the country, is growing. Members of a women's rights group have sought the support of the NCW to abolish the practice of triple talaq.<br />]]></magazinekicker><tags>
<tag>333831</tag>
</tags>
<shortheadline><![CDATA[Time for Uniform Civil Code? 50,000 Muslims sign up against triple talaq]]></shortheadline>
<storytitle><![CDATA[Time for Uniform Civil Code? 50,000 Muslims sign up against triple talaq]]></storytitle>
<short_introtext><![CDATA[]]></short_introtext>
<magazineheadline><![CDATA[]]></magazineheadline>
<longheadline><![CDATA[Time for Uniform Civil Code? 50,000 Muslims sign up against triple talaq]]></longheadline>
<strapheadline><![CDATA[]]></strapheadline>
<storyrating/>
<like_dislike>
<like>7</like>
<dislike>1</dislike>
</like_dislike>
<newtitle/>
<redirectionurl><![CDATA[http://indiatoday.intoday.in/story/triple-talaq-muslim-women-national-commission-for-women/1/682295.html]]></redirectionurl>
<courtesy><![CDATA[]]></courtesy>
<snappost>no</snappost>
<socialmediaintegration>
<facebook/>
<facebook_instant_article>1</facebook_instant_article>
<twitter/>
</socialmediaintegration>
<facebook_instant_article_integration>
<facebook_instant_article>1</facebook_instant_article>
<audio_position>0</audio_position>
<audio_url><![CDATA[]]></audio_url>
<animated_image_position>0</animated_image_position>
<animated_image><![CDATA[]]></animated_image>
<map_embed_code_position>0</map_embed_code_position>
<map_embed_code><![CDATA[]]></map_embed_code>
<gallery_associate_content>
<gallery_associate>
<gallery_id_position/>
<gallery_id/>
</gallery_associate>
</gallery_associate_content>
<social_embed_code_position>0</social_embed_code_position>
<social_embed_code><![CDATA[]]></social_embed_code>
</facebook_instant_article_integration>
<facebooknarrative><![CDATA[Time for Uniform Civil Code? 50,000 Muslims sign up against triple talaq]]></facebooknarrative>
<facebookimage><![CDATA[http://media2.intoday.in/indiatoday/images/stories/sc-8_647_032916081957_060116124839.jpg]]></facebookimage>
<facebookvideonarrative/>
<facebookvideo/>
<twitternarrative><![CDATA[Time for Uniform Civil Code? 50,000 Muslims sign up against triple talaq]]></twitternarrative>
<twitterimage><![CDATA[http://media2.intoday.in/indiatoday/images/stories/sc-8_647_032916081957_060116124839.jpg]]></twitterimage>
<twittervideodescription/>
<twittervideo/>
<syndication>1</syndication>
<syndications_photo>0</syndications_photo>
<noindex_nofollow>0</noindex_nofollow>
<content_type_tag/>
<configurations>
<breakingnews>0</breakingnews>
<googlestandout>0</googlestandout>
<comment>0</comment>
<mediumstylecomment>0</mediumstylecomment>
<displaylock>0</displaylock>
</configurations>
<commentbox>1</commentbox>
<commentquestion/>
<featuredname/>
<relatedcontents/>
<scheduledatetime/>
<storyexpires/>
<storyexpirydate/>
<selectlisticletemplates/>
<quotes>
<quote><![CDATA[]]></quote>
</quotes>
<blurbs>
<blurb/>
</blurbs>
<tables>
<table><![CDATA[]]></table>
</tables>
<external_url/>
<buzz_content>
<buzz>
<headline/>
<image/>
<description/>
</buzz>
<buzz>
<headline/>
<image/>
<description/>
</buzz>
</buzz_content>
<briefcase_content><briefcase><![CDATA[Women's rights group wants Muslim personal law to be amended to safeguard women's rights.]]></briefcase><briefcase><![CDATA[The body claims that 92 per cent Muslim women are against triple talaq.]]></briefcase></briefcase_content><expertname/>
<expertimage/>
<expertdescription/>
<archive/>
<associatetvdate/>
<metatags>
<sefurl><![CDATA[triple-talaq-muslim-women-national-commission-for-women]]></sefurl>
<pagetitle><![CDATA[Time for Uniform Civil Code? 50,000 Muslims sign up against triple talaq]]></pagetitle>
<keywords><![CDATA[Triple talaq,Muslims,Talaq,Muslim women,National Commission for Women,NCW]]></keywords>
</metatags>
</story>