<story>
<id>683152</id>
<state>1</state>
<story_issue>no</story_issue>
<select_magazine>0</select_magazine>
<select_supplement/>
<issue_date/>
<bylines>
<byline>302</byline>
</bylines>
<createddate>1464838204</createddate>
<publisheddate>1464838110</publisheddate>
<modifieddate>1464838691</modifieddate>
<createdby>781</createdby>
<modifiedby>781</modifiedby>
<cities>
<city>286059</city>
</cities>
<categories><category>938494</category></categories><ordering>683150</ordering><primarycategory>938494</primarycategory><extralargeimage><![CDATA[http://media2.intoday.in/indiatoday/images/stories/google_559_060216090800.jpg]]></extralargeimage>
<extra_large_alt/>
<extra_large_title/>
<largeimage><![CDATA[http://media2.intoday.in/indiatoday/images/stories/google_305_060216090800.jpg]]></largeimage>
<large_alt/>
<large_title/>
<mediumimage/>
<mediumimage_alt/>
<mediumimage_title/>
<smallimage><![CDATA[http://media2.intoday.in/indiatoday/images/stories/google_180_060216090800.jpg]]></smallimage>
<smallimage_alt/>
<smallimage_title/>
<extrasmallimage><![CDATA[http://media2.intoday.in/indiatoday/images/stories/google_88_060216090800.jpg]]></extrasmallimage>
<extra_small_alt/>
<extra_small_title/>
<bigimage/>
<kicker_image_caption/>
<mosimage>
<image/><caption/></mosimage>
<pros_cons><tech_pros_cons_main><title/><rating/><pron_cons_img/></tech_pros_cons_main><tech_pros><item/><item/><item/></tech_pros><tech_cons><item/><item/></tech_cons></pros_cons><tech-image-gallery><image/></tech-image-gallery><fulltext_conclaveformat><listicle_title/>
<quote_title/>
<quote_image/>
<factoids_title/>
<listicle_content><listicle/>
</listicle_content>
<quotes><quote/>
</quotes>
<factoids_content><factoids/>
</factoids_content>
</fulltext_conclaveformat>
<storykicker><![CDATA[In coming weeks, a shortcut to personal account information will appear 
at the top of Google's search results whenever logged-in users enter 
their own names in the query box.]]></storykicker>
<storybody><![CDATA[<p>Soon, all you'll need to do is Google yourself if you're wondering how deeply Google has been digging into your digital life.</p><p>In coming weeks, a shortcut to personal account information will appear at the top of Google's search results whenever logged-in users enter their own names in the query box.</p><p>The feature is part of an update to the "My Account" hub that Google introduced a year ago to make it easier for people to manage the privacy and security controls on the internet company's services. While Google isn't making any additional information available, it is making it easier to find.</p><p>The link to personal accounts will appear at the top right of the listings for searches done on personal computers and at the top of requests entered on smartphones.</p><p>Google is making the change because it learned that many users doing a "vanity search" under their name wanted a quicker way to find out what the company knew about them, as well as to see how they are depicted on various sites across the internet, said Guemmy Kim, a Google product manager.</p><p>A new feature on Google's mobile app will also quickly take users to their account information with a spoken request. All that will be required are the words: "OK Google, show me my Google account." This option initially will only be available in English.</p><p class="review_also_read"><strong>Also read: </strong> <a href="http://indiatoday.intoday.in/technology/story/hush-facebook-is-listening-you-conversations-possibly-all-of-them/1/682457.html
" title="">

Hush! Facebook is listening to your conversations. Possibly all of them

</a></p><p>People have become more interested in managing their digital profiles as a confluence of search engines, smartphones and online social networks makes it easier to track where they are, what they're doing and what they're thinking. Revelations about government agencies' online surveillance programs also has heightened interest in privacy protection.</p><p>Google uses the data collected by its search engine, Gmail and other services to analyze people's interests and habits to show them ads about products most likely to appeal to them. Those ads generated $67 billion in revenue last year, providing most of the money that fuels Google's parent company, Alphabet Inc.</p><p>In addition to providing quicker ways to get to personal account information, Google also is introducing a "Find Your Phone" tool that's designed to protect data stored on a device, as well as help locate it if it's lost or stolen. The tool will work on Apple's iPhone, as well as devices running on Google's Android software. It's meant to supplement the device-tracking and security features already built into the iPhone and the Android operating system.</p><p class="review_also_read"><strong>Also read: </strong> <a href="http://indiatoday.intoday.in/technology/story/no-app-required-google-search-brings-weather-directly-to-your-home-screen/1/671431.html " mce_href="http://indiatoday.intoday.in/technology/story/no-app-required-google-search-brings-weather-directly-to-your-home-screen/1/671431.html " title="">  No app required, Google search brings weather directly to your home screen  </a></p>]]></storybody>
<magazinekicker><![CDATA[In coming weeks, a shortcut to personal account information will appear 
at the top of Google's search results whenever logged-in users enter 
their own names in the query box.]]></magazinekicker><tags>
<tag>234886</tag>
<tag>494186</tag>
<tag>621969</tag>
<tag>224533</tag>
<tag>275376</tag>
<tag>231819</tag>
</tags>
<shortheadline><![CDATA[Now you can control what Google search shows about you]]></shortheadline>
<storytitle><![CDATA[Now you can control what Google search shows about you]]></storytitle>
<short_introtext><![CDATA[]]></short_introtext>
<magazineheadline><![CDATA[]]></magazineheadline>
<longheadline><![CDATA[Now you can control what Google search shows about you]]></longheadline>
<strapheadline><![CDATA[]]></strapheadline>
<storyrating/>
<like_dislike>
<like>0</like>
<dislike>0</dislike>
</like_dislike>
<newtitle/>
<redirectionurl><![CDATA[http://indiatoday.intoday.in/technology/story/now-you-can-control-what-google-search-shows-about-you/1/683152.html]]></redirectionurl>
<courtesy><![CDATA[]]></courtesy>
<snappost>no</snappost>
<socialmediaintegration>
<facebook/>
<facebook_instant_article>1</facebook_instant_article>
<twitter/>
</socialmediaintegration>
<facebook_instant_article_integration>
<facebook_instant_article>1</facebook_instant_article>
<audio_position>0</audio_position>
<audio_url><![CDATA[]]></audio_url>
<animated_image_position>0</animated_image_position>
<animated_image><![CDATA[]]></animated_image>
<map_embed_code_position>0</map_embed_code_position>
<map_embed_code><![CDATA[]]></map_embed_code>
<gallery_associate_content>
<gallery_associate>
<gallery_id_position/>
<gallery_id/>
</gallery_associate>
</gallery_associate_content>
<social_embed_code_position>0</social_embed_code_position>
<social_embed_code><![CDATA[]]></social_embed_code>
</facebook_instant_article_integration>
<facebooknarrative><![CDATA[Now you can control what Google search shows about you]]></facebooknarrative>
<facebookimage><![CDATA[http://media2.intoday.in/indiatoday/images/stories/google_559_060216090800.jpg]]></facebookimage>
<facebookvideonarrative/>
<facebookvideo/>
<twitternarrative><![CDATA[Now you can control what Google search shows about you]]></twitternarrative>
<twitterimage><![CDATA[http://media2.intoday.in/indiatoday/images/stories/google_559_060216090800.jpg]]></twitterimage>
<twittervideodescription/>
<twittervideo/>
<syndication>1</syndication>
<syndications_photo>0</syndications_photo>
<noindex_nofollow>0</noindex_nofollow>
<content_type_tag/>
<configurations>
<breakingnews>0</breakingnews>
<googlestandout>0</googlestandout>
<comment>0</comment>
<mediumstylecomment>0</mediumstylecomment>
<displaylock>0</displaylock>
</configurations>
<commentbox>1</commentbox>
<commentquestion/>
<featuredname/>
<relatedcontents/>
<scheduledatetime/>
<storyexpires/>
<storyexpirydate/>
<selectlisticletemplates/>
<quotes>
<quote><![CDATA[]]></quote>
</quotes>
<blurbs>
<blurb/>
</blurbs>
<tables>
<table><![CDATA[]]></table>
</tables>
<external_url/>
<buzz_content>
<buzz>
<headline/>
<image/>
<description/>
</buzz>
<buzz>
<headline/>
<image/>
<description/>
</buzz>
</buzz_content>
<briefcase_content><briefcase/></briefcase_content><expertname/>
<expertimage/>
<expertdescription/>
<archive/>
<associatetvdate/>
<metatags>
<sefurl><![CDATA[now-you-can-control-what-google-search-shows-about-you]]></sefurl>
<pagetitle><![CDATA[Now you can control what Google search shows about you]]></pagetitle>
<keywords><![CDATA[google search, google my account, google privacy control, google account security]]></keywords>
</metatags>
</story>