<story>
<id>683262</id>
<state>1</state>
<story_issue>no</story_issue>
<select_magazine>0</select_magazine>
<select_supplement/>
<issue_date/>
<bylines>
<byline>290</byline>
</bylines>
<createddate>1464862507</createddate>
<publisheddate>1464862197</publisheddate>
<modifieddate>1464869608</modifieddate>
<createdby>887</createdby>
<modifiedby>887</modifiedby>
<cities>
<city/>
</cities>
<categories><category>279970</category><category>280038</category><category>938414</category><category>938659</category></categories><ordering>683262</ordering><primarycategory>938659</primarycategory><extralargeimage><![CDATA[http://media2.intoday.in/indiatoday/images/stories/nandisharjun-647_060216034507.jpg]]></extralargeimage>
<extra_large_alt><![CDATA[Nandish Sandhu might join Naagin 2; Arjun Bijlani will not be part of the second season.]]></extra_large_alt>
<extra_large_title><![CDATA[Nandish Sandhu might join Naagin 2; Arjun Bijlani will not be part of the second season.]]></extra_large_title>
<largeimage><![CDATA[http://media2.intoday.in/indiatoday/images/stories/nandisharjun-305_060216034507.jpg]]></largeimage>
<large_alt><![CDATA[Nandish Sandhu might join Naagin 2; Arjun Bijlani will not be part of the second season.]]></large_alt>
<large_title><![CDATA[Nandish Sandhu might join Naagin 2; Arjun Bijlani will not be part of the second season.]]></large_title>
<mediumimage><![CDATA[http://media2.intoday.in/indiatoday/images/stories/nandisharjun-300_060216034507.jpg]]></mediumimage>
<mediumimage_alt><![CDATA[Nandish Sandhu might join Naagin 2; Arjun Bijlani will not be part of the second season.]]></mediumimage_alt>
<mediumimage_title><![CDATA[Nandish Sandhu might join Naagin 2; Arjun Bijlani will not be part of the second season.]]></mediumimage_title>
<smallimage><![CDATA[http://media2.intoday.in/indiatoday/images/stories/nandisharjun-180_060216034507.jpg]]></smallimage>
<smallimage_alt><![CDATA[Nandish Sandhu might join Naagin 2; Arjun Bijlani will not be part of the second season.]]></smallimage_alt>
<smallimage_title><![CDATA[Nandish Sandhu might join Naagin 2; Arjun Bijlani will not be part of the second season.]]></smallimage_title>
<extrasmallimage><![CDATA[http://media2.intoday.in/indiatoday/images/stories/nandisharjun-88_060216034507.jpg]]></extrasmallimage>
<extra_small_alt><![CDATA[Nandish Sandhu might join Naagin 2; Arjun Bijlani will not be part of the second season.]]></extra_small_alt>
<extra_small_title><![CDATA[Nandish Sandhu might join Naagin 2; Arjun Bijlani will not be part of the second season.]]></extra_small_title>
<bigimage/>
<kicker_image_caption><![CDATA[Nandish Sandhu might join Naagin 2; Arjun Bijlani will not be part of the second season.]]></kicker_image_caption>
<mosimage>
<image/><caption/></mosimage>
<pros_cons><tech_pros_cons_main><title/><rating/><pron_cons_img/></tech_pros_cons_main><tech_pros><item/><item/><item/></tech_pros><tech_cons><item/><item/></tech_cons></pros_cons><tech-image-gallery><image/></tech-image-gallery><fulltext_conclaveformat><listicle_title/>
<quote_title/>
<quote_image/>
<factoids_title/>
<listicle_content><listicle/>
</listicle_content>
<quotes><quote/>
</quotes>
<factoids_content><factoids/>
</factoids_content>
</fulltext_conclaveformat>
<storykicker><![CDATA[Apparently, Mouni Roy will play Ritik and Shivanya's daughter in the next season.]]></storykicker>
<storybody><![CDATA[<p>The last episode of the first season of Naagin will air on June 5 and Ekta Kapoor's supernatural show Kawach will replace Mouni Roy-Arjun Bijlani starrer. </p><p>Good news is that the second season will go on the floors in less than 100 days from now, according to reports. </p><p>However, Season 2 will apparently not star TV's current heartthrob Arjun Bijlani. Mouni Roy will continue to be the protagonist of the show; she'll play Shivanya and Ritik's daughter. Also, Nandish Sandhu of Uttaran fame is expected to be part of Naagin 2. </p><p><u><b><a href="http://indiatoday.intoday.in/story/naagin-mouni-roy-arjun-bijlani-adaa-khan-last-day/1/679674.html" mce_href="http://indiatoday.intoday.in/story/naagin-mouni-roy-arjun-bijlani-adaa-khan-last-day/1/679674.html">Also read: Naagin team says goodbye; Mouni Roy, Arjun Bijlani, Adaa Khan click selfies on last day </a></b></u> <br /></p><p>Aashka Goradia has already joined the cast of Naagin as the Queen of Mahishmati and will be seen in a prominent role in the second season.</p><p>Apart from Aashka, a host of other baddies will be added to the cast. So, if you are heartbroken with the news of Naagin going off air, it's time to celebrate now.</p><p><u><b><a href="http://indiatoday.intoday.in/story/four-shocking-twists-you-can-expect-in-naagin-finale/1/675918.html" mce_href="http://indiatoday.intoday.in/story/four-shocking-twists-you-can-expect-in-naagin-finale/1/675918.html">Also read: Four shocking twists you can expect to see in the Naagin finale </a></b></u> <br /></p>]]></storybody>
<magazinekicker><![CDATA[Apparently, Mouni Roy will play Ritik and Shivanya's daughter in the next season.]]></magazinekicker><tags>
<tag>259983</tag>
<tag>333440</tag>
<tag>225109</tag>
<tag>239976</tag>
<tag>613504</tag>
</tags>
<shortheadline><![CDATA[Naagin 2: Nandish Sandhu in; Arjun Bijlani out?]]></shortheadline>
<storytitle><![CDATA[Naagin 2: Nandish Sandhu in; Arjun Bijlani out?]]></storytitle>
<short_introtext><![CDATA[]]></short_introtext>
<magazineheadline><![CDATA[]]></magazineheadline>
<longheadline><![CDATA[Naagin 2: Nandish Sandhu in; Arjun Bijlani out?]]></longheadline>
<strapheadline><![CDATA[]]></strapheadline>
<storyrating/>
<like_dislike>
<like>9</like>
<dislike>14</dislike>
</like_dislike>
<newtitle/>
<redirectionurl><![CDATA[http://indiatoday.intoday.in/story/naagin-2-nandish-sandhu-in-arjun-bijlani-out-mouni-roy-aashka-goradia-lifetv/1/683262.html]]></redirectionurl>
<courtesy><![CDATA[]]></courtesy>
<snappost>no</snappost>
<socialmediaintegration>
<facebook/>
<facebook_instant_article>1</facebook_instant_article>
<twitter/>
</socialmediaintegration>
<facebook_instant_article_integration>
<facebook_instant_article>1</facebook_instant_article>
<audio_position>0</audio_position>
<audio_url><![CDATA[]]></audio_url>
<animated_image_position>0</animated_image_position>
<animated_image><![CDATA[]]></animated_image>
<map_embed_code_position>0</map_embed_code_position>
<map_embed_code><![CDATA[]]></map_embed_code>
<gallery_associate_content>
<gallery_associate>
<gallery_id_position/>
<gallery_id/>
</gallery_associate>
</gallery_associate_content>
<social_embed_code_position>0</social_embed_code_position>
<social_embed_code><![CDATA[]]></social_embed_code>
</facebook_instant_article_integration>
<facebooknarrative><![CDATA[Naagin 2: Nandish Sandhu in; Arjun Bijlani out?]]></facebooknarrative>
<facebookimage><![CDATA[http://media2.intoday.in/indiatoday/images/stories/nandisharjun-647_060216034507.jpg]]></facebookimage>
<facebookvideonarrative/>
<facebookvideo/>
<twitternarrative><![CDATA[Naagin 2: Nandish Sandhu in; Arjun Bijlani out?]]></twitternarrative>
<twitterimage><![CDATA[http://media2.intoday.in/indiatoday/images/stories/nandisharjun-647_060216034507.jpg]]></twitterimage>
<twittervideodescription/>
<twittervideo/>
<syndication>1</syndication>
<syndications_photo>0</syndications_photo>
<noindex_nofollow>0</noindex_nofollow>
<content_type_tag/>
<configurations>
<breakingnews>0</breakingnews>
<googlestandout>0</googlestandout>
<comment>0</comment>
<mediumstylecomment>0</mediumstylecomment>
<displaylock>0</displaylock>
</configurations>
<commentbox>1</commentbox>
<commentquestion/>
<featuredname/>
<relatedcontents><relatedcontent type="text">679674</relatedcontent><relatedcontent type="text">675918</relatedcontent><relatedcontent type="text">675521</relatedcontent><relatedcontent type="text">671153</relatedcontent><relatedcontent type="text">666237</relatedcontent><relatedcontent type="text">663918</relatedcontent><relatedcontent type="text">659705</relatedcontent><relatedcontent type="text">658588</relatedcontent><relatedcontent type="text">658573</relatedcontent></relatedcontents>
<scheduledatetime/>
<storyexpires/>
<storyexpirydate/>
<selectlisticletemplates/>
<quotes>
<quote><![CDATA[]]></quote>
</quotes>
<blurbs>
<blurb/>
</blurbs>
<tables>
<table><![CDATA[]]></table>
</tables>
<external_url/>
<buzz_content>
<buzz>
<headline/>
<image/>
<description/>
</buzz>
<buzz>
<headline/>
<image/>
<description/>
</buzz>
</buzz_content>
<briefcase_content><briefcase/></briefcase_content><expertname/>
<expertimage/>
<expertdescription/>
<archive/>
<associatetvdate/>
<metatags>
<sefurl><![CDATA[naagin-2-nandish-sandhu-in-arjun-bijlani-out-mouni-roy-aashka-goradia-lifetv]]></sefurl>
<pagetitle><![CDATA[Naagin 2: Nandish Sandhu in; Arjun Bijlani out?]]></pagetitle>
<keywords><![CDATA[Mouni Roy, Arjun Bijlani, Nandish Sandhu, Aashka Goradia, Naagin 2]]></keywords>
</metatags>
</story>