<story>
<id>683320</id>
<state>1</state>
<story_issue>no</story_issue>
<select_magazine>0</select_magazine>
<select_supplement/>
<issue_date/>
<bylines>
<byline>290</byline>
</bylines>
<createddate>1464871587</createddate>
<publisheddate>1464871519</publisheddate>
<modifieddate>1464872574</modifieddate>
<createdby>860</createdby>
<modifiedby>860</modifiedby>
<cities>
<city>285563</city>
</cities>
<categories><category>279970</category><category>280038</category><category>280225</category><category>279986</category><category>279603</category></categories><ordering>683320</ordering><primarycategory>279603</primarycategory><extralargeimage><![CDATA[http://media2.intoday.in/indiatoday/images/stories/aussgirl---facebook-and-storysize_647_060216063235.jpg]]></extralargeimage>
<extra_large_alt/>
<extra_large_title/>
<largeimage><![CDATA[http://media2.intoday.in/indiatoday/images/stories/aussgirl---facebook-and-storysize_305_060216063235.jpg]]></largeimage>
<large_alt/>
<large_title/>
<mediumimage><![CDATA[http://media2.intoday.in/indiatoday/images/stories/aussgirl---facebook-and-storysize_300_060216063235.jpg]]></mediumimage>
<mediumimage_alt/>
<mediumimage_title/>
<smallimage><![CDATA[http://media2.intoday.in/indiatoday/images/stories/aussgirl---facebook-and-storysize_180_060216063235.jpg]]></smallimage>
<smallimage_alt/>
<smallimage_title/>
<extrasmallimage><![CDATA[http://media2.intoday.in/indiatoday/images/stories/aussgirl---facebook-and-storysize_88_060216063235.jpg]]></extrasmallimage>
<extra_small_alt/>
<extra_small_title/>
<bigimage/>
<kicker_image_caption><![CDATA[Picture for representation. Photo:mentalhealthrehab.com]]></kicker_image_caption>
<mosimage>
<image/><caption/></mosimage>
<pros_cons><tech_pros_cons_main><title/><rating/><pron_cons_img/></tech_pros_cons_main><tech_pros><item/><item/><item/></tech_pros><tech_cons><item/><item/></tech_cons></pros_cons><tech-image-gallery><image/></tech-image-gallery><fulltext_conclaveformat><listicle_title/>
<quote_title/>
<quote_image/>
<factoids_title/>
<listicle_content><listicle/>
</listicle_content>
<quotes><quote/>
</quotes>
<factoids_content><factoids/>
</factoids_content>
</fulltext_conclaveformat>
<storykicker><![CDATA[A woman got involved in a relationship with her adult nephew. She assisted him in the rape of her 12-year-old daughter in 2011. <br />]]></storykicker>
<storybody><![CDATA[<p>A woman, accused of being involved in a sexual (incestuous) relationship with her 42-year-old nephew, helped him rape her 12-year-old daughter.</p><p>The girl was raped for the first time in 2011 and has been a victim of sexual abuse till 2014. The accused cannot be named for legal reasons, but the man pleaded guilty in the County Court of Victoria yesterday. </p><p>"The 55-year-old woman pleaded guilty to sexual penetration of a child and an indecent act with a child," reports news.com.au. </p><p>The woman's relationship with her nephew began shortly after she, along with her daughter, moved in to one of his houses in Melbourne after she separated from her husband. The nephew was arrested in December 2014. The victim had opened up to her older siblings about the rapes. </p><p>Both the accused were out on bail, but the woman has been remanded in custody since March, for she broke her bail conditions and attempted to contact her daughter. </p><p>Judge Clare Quin wasn't convinced about a letter the nephew's lawyer, Ashley Halphen, produced before the court to prove he expressed remorse. </p><p>The court was adjourned till Friday. <br /></p>]]></storybody>
<magazinekicker><![CDATA[A woman got involved in a relationship with her adult nephew. She assisted him in the rape of her 12-year-old daughter in 2011. <br />]]></magazinekicker><tags>
<tag>267982</tag>
<tag>225876</tag>
</tags>
<shortheadline><![CDATA[Aussie woman in relationship with nephew helped him rape her daughter]]></shortheadline>
<storytitle><![CDATA[Aussie woman in relationship with nephew helped him rape her daughter]]></storytitle>
<short_introtext><![CDATA[]]></short_introtext>
<magazineheadline><![CDATA[]]></magazineheadline>
<longheadline><![CDATA[Aussie woman in relationship with nephew helped him rape her daughter]]></longheadline>
<strapheadline><![CDATA[]]></strapheadline>
<storyrating/>
<like_dislike>
<like>0</like>
<dislike>1</dislike>
</like_dislike>
<newtitle/>
<redirectionurl><![CDATA[http://indiatoday.intoday.in/story/australia-woman-incest-relationship-nephew-help-rape-daughter/1/683320.html]]></redirectionurl>
<courtesy><![CDATA[]]></courtesy>
<snappost>no</snappost>
<socialmediaintegration>
<facebook/>
<facebook_instant_article>1</facebook_instant_article>
<twitter/>
</socialmediaintegration>
<facebook_instant_article_integration>
<facebook_instant_article>1</facebook_instant_article>
<audio_position>0</audio_position>
<audio_url><![CDATA[]]></audio_url>
<animated_image_position>0</animated_image_position>
<animated_image><![CDATA[]]></animated_image>
<map_embed_code_position>0</map_embed_code_position>
<map_embed_code><![CDATA[]]></map_embed_code>
<gallery_associate_content>
<gallery_associate>
<gallery_id_position/>
<gallery_id/>
</gallery_associate>
</gallery_associate_content>
<social_embed_code_position>0</social_embed_code_position>
<social_embed_code><![CDATA[]]></social_embed_code>
</facebook_instant_article_integration>
<facebooknarrative><![CDATA[Aussie woman in relationship with nephew helped him rape her daughter]]></facebooknarrative>
<facebookimage><![CDATA[http://media2.intoday.in/indiatoday/images/stories/aussgirl---facebook-and-storysize_647_060216063235.jpg]]></facebookimage>
<facebookvideonarrative/>
<facebookvideo/>
<twitternarrative><![CDATA[Aussie woman in relationship with nephew helped him rape her daughter]]></twitternarrative>
<twitterimage><![CDATA[http://media2.intoday.in/indiatoday/images/stories/aussgirl---facebook-and-storysize_647_060216063235.jpg]]></twitterimage>
<twittervideodescription/>
<twittervideo/>
<syndication>1</syndication>
<syndications_photo>0</syndications_photo>
<noindex_nofollow>0</noindex_nofollow>
<content_type_tag/>
<configurations>
<breakingnews>0</breakingnews>
<googlestandout>0</googlestandout>
<comment>0</comment>
<mediumstylecomment>0</mediumstylecomment>
<displaylock>0</displaylock>
</configurations>
<commentbox>1</commentbox>
<commentquestion/>
<featuredname/>
<relatedcontents/>
<scheduledatetime/>
<storyexpires/>
<storyexpirydate/>
<selectlisticletemplates/>
<quotes>
<quote><![CDATA[]]></quote>
</quotes>
<blurbs>
<blurb/>
</blurbs>
<tables>
<table><![CDATA[]]></table>
</tables>
<external_url/>
<buzz_content>
<buzz>
<headline/>
<image/>
<description/>
</buzz>
<buzz>
<headline/>
<image/>
<description/>
</buzz>
</buzz_content>
<briefcase_content><briefcase/></briefcase_content><expertname/>
<expertimage/>
<expertdescription/>
<archive/>
<associatetvdate/>
<metatags>
<sefurl><![CDATA[australia-woman-incest-relationship-nephew-help-rape-daughter]]></sefurl>
<pagetitle><![CDATA[Aussie woman in relationship with nephew helped him rape her daughter]]></pagetitle>
<keywords><![CDATA[Rape, Incest, Mother Helps Nephew Rape Daughter, County Court, Melbourne]]></keywords>
</metatags>
</story>