<story>
<id>683319</id>
<state>1</state>
<story_issue>no</story_issue>
<select_magazine>0</select_magazine>
<select_supplement/>
<issue_date/>
<bylines>
<byline>500</byline>
</bylines>
<createddate>1464871573</createddate>
<publisheddate>1464871429</publisheddate>
<modifieddate>1464877117</modifieddate>
<createdby>904</createdby>
<modifiedby>906</modifiedby>
<cities>
<city>285729</city>
</cities>
<categories><category>937816</category><category>279998</category><category>280607</category></categories><ordering>683280</ordering><primarycategory>937816</primarycategory><extralargeimage><![CDATA[http://media2.intoday.in/indiatoday/images/stories/647_060216061613.jpg]]></extralargeimage>
<extra_large_alt/>
<extra_large_title/>
<largeimage><![CDATA[http://media2.intoday.in/indiatoday/images/stories/305_060216061613.jpg]]></largeimage>
<large_alt/>
<large_title/>
<mediumimage><![CDATA[http://media2.intoday.in/indiatoday/images/stories/300_060216061613.jpg]]></mediumimage>
<mediumimage_alt/>
<mediumimage_title/>
<smallimage><![CDATA[http://media2.intoday.in/indiatoday/images/stories/180_060216061613.jpg]]></smallimage>
<smallimage_alt/>
<smallimage_title/>
<extrasmallimage><![CDATA[http://media2.intoday.in/indiatoday/images/stories/88_060216061613.jpg]]></extrasmallimage>
<extra_small_alt/>
<extra_small_title/>
<bigimage/>
<kicker_image_caption><![CDATA[File photo of Sania Mirza. (Reuters Photo)]]></kicker_image_caption>
<mosimage>
<image/><caption/></mosimage>
<pros_cons><tech_pros_cons_main><title/><rating/><pron_cons_img/></tech_pros_cons_main><tech_pros><item/><item/><item/></tech_pros><tech_cons><item/><item/></tech_cons></pros_cons><tech-image-gallery><image/></tech-image-gallery><fulltext_conclaveformat><listicle_title/>
<quote_title/>
<quote_image/>
<factoids_title/>
<listicle_content><listicle/>
</listicle_content>
<quotes><quote/>
</quotes>
<factoids_content><factoids/>
</factoids_content>
</fulltext_conclaveformat>
<storykicker><![CDATA[Sania Mirza and her mixed doubles partner Ivan Dodig beat Jan Chan and Max Mirnyi 6-1, 3-6, 10-6.]]></storykicker>
<storybody><![CDATA[<p>India's tennis stars Sania Mirza and Leander Paes today reached the French Open mixed doubles semi-finals with their respective partners.</p><p>Sania and her mixed doubles partner Ivan Dodig beat Jan Chan and Max Mirnyi to move into the semi-finals of the French Open tennis tournament The second seeds won the contest in the tie-breaker with a 6-1, 3-6, 10-6 on Court 2.</p><p>Later in the day, Paes and Martina Hingis overwhelmed fifth seeds Bruno Soares and Elena Vesnina 6-4, 6-3.</p><p>The Indo-Swiss pair were dominant throughout the match, using their vast experience to good effect, breaking their Brazil-Russian opponent four times in 11 attempts.</p><p>They were broken just once in five tries. Paes-Hingis won 60 of the total 111 total points played.</p><p>Earlier, Sania and her Croatian partner were able to get into their stride from the beginning and pocketed the first game quite easily against the Chinese Taipei-Belarusian pair.</p><p>They then broke their opponents to move ahead 2-0 in the first set. And though Chan and Mirnyi tried catching up, the Indo-Croatian pair remained ahead.</p><p>Before long it was 5-0 and Sania-Ivan ensured there were no hiccups as they pocketed the opening set 6-1.</p><p>Jan-Max scripted a turnaround in the second set. The Chinese Taipei-Belarusian pair rallied back into the contest by pocketing three back to back games to march to a 4-1 lead.</p><p>Sania-Ivan broke back to reduce the margin to 3-5 but Jan-Max sealed the set by winning their service game to stretch the match into a deciding tie-breaker.</p><p>The Sania-Ivan pair was brilliant in the tie breaker and had things under control from the very beginning. They led 8-5 at one stage and finally bought the shutters down at 10-6.</p>]]></storybody>
<magazinekicker><![CDATA[Sania Mirza and her mixed doubles partner Ivan Dodig beat Jan Chan and Max Mirnyi 6-1, 3-6, 10-6.]]></magazinekicker><tags>
<tag>223112</tag>
<tag>494219</tag>
<tag>231064</tag>
<tag>222524</tag>
<tag>247199</tag>
</tags>
<shortheadline><![CDATA[French Open: Sania storms into mixed doubles semis, Paes follows suit]]></shortheadline>
<storytitle><![CDATA[French Open: Sania Mirza storms into mixed doubles semis, Leander Paes follows suit]]></storytitle>
<short_introtext><![CDATA[]]></short_introtext>
<magazineheadline><![CDATA[]]></magazineheadline>
<longheadline><![CDATA[French Open: Sania Mirza storms into mixed doubles semis, Leander Paes follows suit]]></longheadline>
<strapheadline><![CDATA[Sania Mirza can win French Open mixed doubles title]]></strapheadline>
<storyrating/>
<like_dislike>
<like>0</like>
<dislike>0</dislike>
</like_dislike>
<newtitle/>
<redirectionurl><![CDATA[http://indiatoday.intoday.in/story/sania-mirza-ivan-dodig-french-open-mixed-doubles/1/683319.html]]></redirectionurl>
<courtesy><![CDATA[]]></courtesy>
<snappost>yes</snappost>
<socialmediaintegration>
<facebook/>
<facebook_instant_article>1</facebook_instant_article>
<twitter/>
</socialmediaintegration>
<facebook_instant_article_integration>
<facebook_instant_article>1</facebook_instant_article>
<audio_position>0</audio_position>
<audio_url><![CDATA[]]></audio_url>
<animated_image_position>0</animated_image_position>
<animated_image><![CDATA[]]></animated_image>
<map_embed_code_position>0</map_embed_code_position>
<map_embed_code><![CDATA[]]></map_embed_code>
<gallery_associate_content>
<gallery_associate>
<gallery_id_position/>
<gallery_id/>
</gallery_associate>
</gallery_associate_content>
<social_embed_code_position>0</social_embed_code_position>
<social_embed_code><![CDATA[]]></social_embed_code>
</facebook_instant_article_integration>
<facebooknarrative><![CDATA[French Open: Sania storms into mixed doubles semis, Paes follows suit]]></facebooknarrative>
<facebookimage><![CDATA[http://media2.intoday.in/indiatoday/images/stories/647_060216061613.jpg]]></facebookimage>
<facebookvideonarrative/>
<facebookvideo/>
<twitternarrative><![CDATA[French Open: Sania storms into mixed doubles semis, Paes follows suit]]></twitternarrative>
<twitterimage><![CDATA[http://media2.intoday.in/indiatoday/images/stories/647_060216061613.jpg]]></twitterimage>
<twittervideodescription/>
<twittervideo/>
<syndication>0</syndication>
<syndications_photo>0</syndications_photo>
<noindex_nofollow>0</noindex_nofollow>
<content_type_tag/>
<configurations>
<breakingnews>0</breakingnews>
<googlestandout>1</googlestandout>
<comment>0</comment>
<mediumstylecomment>0</mediumstylecomment>
<displaylock>0</displaylock>
</configurations>
<commentbox>1</commentbox>
<commentquestion/>
<featuredname/>
<relatedcontents/>
<scheduledatetime/>
<storyexpires/>
<storyexpirydate/>
<selectlisticletemplates/>
<quotes>
<quote><![CDATA[]]></quote>
</quotes>
<blurbs>
<blurb/>
</blurbs>
<tables>
<table><![CDATA[]]></table>
</tables>
<external_url/>
<buzz_content>
<buzz>
<headline/>
<image/>
<description/>
</buzz>
<buzz>
<headline/>
<image/>
<description/>
</buzz>
</buzz_content>
<briefcase_content><briefcase><![CDATA[Sania and Dodig are seeded second in the tournament.]]></briefcase><briefcase><![CDATA[Sania is aiming for her second mixed doubles title at Roland Garros.]]></briefcase><briefcase><![CDATA[She won the French Open in 2012 with Mahesh Bhupathi.]]></briefcase></briefcase_content><expertname/>
<expertimage/>
<expertdescription/>
<archive/>
<associatetvdate/>
<metatags>
<sefurl><![CDATA[sania-mirza-ivan-dodig-french-open-mixed-doubles]]></sefurl>
<pagetitle><![CDATA[French Open: Sania storms into mixed doubles semis, Paes follows suit]]></pagetitle>
<keywords><![CDATA[Sania Mirza,Ivan Dodig,French Open,Leander Paes,Martina Hingis]]></keywords>
</metatags>
</story>